{
  "titel": "PRIMEURS ALERT:",
  "rubriek": "de-stem",
  "datum": "3 april 2026",
  "intro": "Ons Koelpietje schrijft geschiedenis! \nJe hebt het vast al voorbij zien komen, de allereerste digitale foto van onze prachtige aarde gaat momenteel viraal.",
  "tekst": "<p>\nPRIMEURS ALERT:\n<p>\nOns Koelpietje schrijft geschiedenis!\nJe hebt het vast al voorbij zien komen, de allereerste digitale foto van onze prachtige aarde gaat momenteel viraal. Een bijzonder moment, want hiervoor moesten we het altijd doen met analoge beelden uit de vorige eeuw!\n<p>",
  "afbeelding": "/uploads/mijnkoelpietje_selfieaarde.jpg",
  "afbeelding_formaat": "staand",
  "id": "Ditishet verhaal"
}
